[
    {
        "name": "CatCalledDog reached 100 subscribers",
        "description": "CCD a PA youtuber reached 100 subscribers.",
        "date": "12/26/21",
        "links": [
            ["CCD channel", "www.youtube.com/channel/UCOjbOh6QM0Rj4J8JYNggdxQ"]
        ]
    },
    {
        "name": "Moderators were added to PA discord",
        "description": "",
        "date": "12/29/21",
        "links": []
    },
    {
        "name": "PA discord server reached 1k members",
        "description": "",
        "date": "12/31/21",
        "links": []
    }
]